{
  "instance": {
    "magic": "APF_VER_1",
    "variant_select": {
      "id": 777,
      "select": false
    },
    "data_slots": [
      {
        "id": 1,
        "filename": "3 Vectrex Academy/Academy 2019/Space Defender_by KusoTech.bin"
      },
      {
        "id": 2,
        "filename": "overlays/academy/SpaceDefender.ovr"
      }
    ],
    "memory_writes": []
  }
}{
  "instance": {
    "magic": "APF_VER_1",
    "variant_select": {
      "id": 777,
      "select": false
    },
    "data_slots": [
      {
        "id": 1,
        "filename": "3 Vectrex Academy/Academy 2019/Space Defender_by KusoTech.bin"
      },
      {
        "id": 2,
        "filename": "overlays/academy/SpaceDefender.ovr"
      }
    ],
    "memory_writes": []
  }
}